{
  "image": "screenshots/screenshot_95.png",
  "resolution": {
    "width": 1536,
    "height": 864
  },
  "widgets": [
    {
      "id": "button_1",
      "type": "Button",
      "text": "ibnynDdotUCIJX",
      "bbox": {
        "x_min": 0,
        "y_min": 60,
        "x_max": 98,
        "y_max": 153
      }
    },
    {
      "id": "label_1",
      "type": "Label",
      "text": "XraWuac",
      "bbox": {
        "x_min": 0,
        "y_min": 560,
        "x_max": 98,
        "y_max": 614
      }
    },
    {
      "id": "button_2",
      "type": "Button",
      "text": "wWiaKQYMfqf",
      "bbox": {
        "x_min": 98,
        "y_min": 60,
        "x_max": 255,
        "y_max": 153
      }
    },
    {
      "id": "entry_1",
      "type": "Entry",
      "text": "",
      "bbox": {
        "x_min": 255,
        "y_min": 60,
        "x_max": 354,
        "y_max": 153
      }
    },
    {
      "id": "entry_2",
      "type": "Entry",
      "text": "",
      "bbox": {
        "x_min": 354,
        "y_min": 0,
        "x_max": 439,
        "y_max": 60
      }
    }
  ]
}